MANIFEST.in
README.md
setup.py
cardholder/__init__.py
cardholder/card_data_interface.py
cardholder/cardholder.py
cardholder/img/spinner.gif
medlib/__init__.py
medlib/card_ini.py
medlib/constants.py
medlib/handle_property.py
medlib/input_output.py
medlib.egg-info/PKG-INFO
medlib.egg-info/SOURCES.txt
medlib.egg-info/dependency_links.txt
medlib.egg-info/entry_points.txt
medlib.egg-info/not-zip-safe
medlib.egg-info/requires.txt
medlib.egg-info/top_level.txt
medlib/dict/resources.properties
medlib/dict/resources_en.properties
medlib/dict/resources_hu.properties
medlib/gui/__init__.py
medlib/gui/control_buttons_holder.py
medlib/gui/medlib_gui.py
medlib/gui/player.py
medlib/gui/images/back-button-off.png
medlib/gui/images/back-button-on.png
medlib/gui/images/hierarchy-button-off.png
medlib/gui/images/hierarchy-button-on.png
medlib/gui/images/medlib.png
medlib/gui/images/play-button.png
medlib/gui/images/stop-button.png
medlib/mediamodel/__init__.py
medlib/mediamodel/extra.py
medlib/mediamodel/ini_classification.py
medlib/mediamodel/ini_control.py
medlib/mediamodel/ini_general.py
medlib/mediamodel/ini_storylines.py
medlib/mediamodel/ini_titles.py
medlib/mediamodel/media_appendix.py
medlib/mediamodel/media_base.py
medlib/mediamodel/media_collector.py
medlib/mediamodel/media_storage.py
medlib/mediamodel/paths_appendix.py
medlib/mediamodel/paths_collector.py
medlib/mediamodel/paths_storage.py
medlib/mediamodel/qlabel_to_link_on_cllick.py
medlib/mediamodel/images/media-collector-audio-audiobook.png
medlib/mediamodel/images/media-collector-audio-music.png
medlib/mediamodel/images/media-collector-audio-presentation.png
medlib/mediamodel/images/media-collector-audio-radioplay.png
medlib/mediamodel/images/media-collector-audio-show.png
medlib/mediamodel/images/media-collector-audio.png
medlib/mediamodel/images/media-collector-elearning.png
medlib/mediamodel/images/media-collector-recipe.png
medlib/mediamodel/images/media-collector-text-book.png
medlib/mediamodel/images/media-collector-text-doc.png
medlib/mediamodel/images/media-collector-text.png
medlib/mediamodel/images/media-collector-video-alternative.png
medlib/mediamodel/images/media-collector-video-family.png
