Metadata-Version: 1.1
Name: medlib
Version: 0.0.7
Summary: Media Library: Media Manager
Home-page: http://github.com/dallaszkorben/medlib
Author: dallaszkorben
Author-email: dallaszkorben@gmail.com
License: MIT
Platform: UNKNOWN
Classifier: Programming Language :: Python
Classifier: Programming Language :: Python :: 3
Classifier: Operating System :: OS Independent
